yil/__init__.py
yil/yil.py
yil-1.3.dist-info/METADATA
yil-1.3.dist-info/WHEEL
yil-1.3.dist-info/entry_points.txt
yil-1.3.dist-info/top_level.txt
yil-1.3.dist-info/RECORD
