Metadata-Version: 2.1
Name: yil
Version: 1.3
Summary: Yandex image loader
Home-page: https://github.com/egm108/YandexImageLoader/tree/main
Author: egm108
Author-email: egm@yandex.ru
License: UNKNOWN
Platform: UNKNOWN
Classifier: Programming Language :: Python :: 3
Classifier: License :: OSI Approved :: MIT License
Classifier: Operating System :: OS Independent
Requires-Python: >=3.8
Requires-Dist: beautifulsoup4 (>=4.11.1)
Requires-Dist: requests (==2.26.0)
